birdhousebuilder.recipe.celery-0.1.1-py2.7-nspkg.pth
birdhousebuilder/recipe/celery/__init__.py
birdhousebuilder/recipe/celery/celery.ini
birdhousebuilder/recipe/celery/celeryconfig.py
birdhousebuilder/recipe/celery/celeryconfig_py
birdhousebuilder/recipe/celery/options.py~
birdhousebuilder/recipe/celery/recipe.rst
birdhousebuilder/recipe/celery/tests/__init__.py
birdhousebuilder/recipe/celery/tests/test_docs.py
birdhousebuilder.recipe.celery-0.1.1.dist-info/DESCRIPTION.rst
birdhousebuilder.recipe.celery-0.1.1.dist-info/METADATA
birdhousebuilder.recipe.celery-0.1.1.dist-info/RECORD
birdhousebuilder.recipe.celery-0.1.1.dist-info/WHEEL
birdhousebuilder.recipe.celery-0.1.1.dist-info/entry_points.txt
birdhousebuilder.recipe.celery-0.1.1.dist-info/metadata.json
birdhousebuilder.recipe.celery-0.1.1.dist-info/namespace_packages.txt
birdhousebuilder.recipe.celery-0.1.1.dist-info/pbr.json
birdhousebuilder.recipe.celery-0.1.1.dist-info/top_level.txt
