Metadata-Version: 2.0
Name: birdhousebuilder.recipe.celery
Version: 0.1.1
Summary: A Buildout recipe to install and configure Celery for Birdhouse.
Home-page: https://github.com/bird-house/birdhousebuilder.recipe.celery
Author: Birdhouse
Author-email: UNKNOWN
License: BSD
Keywords: buildout recipe birdhouse conda celery
Platform: UNKNOWN
Classifier: Framework :: Buildout
Classifier: Intended Audience :: Developers
Classifier: Topic :: Software Development :: Build Tools
Classifier: Topic :: Software Development :: Libraries :: Python Modules
Classifier: License :: OSI Approved :: BSD License
Requires-Dist: Mako
Requires-Dist: birdhousebuilder.recipe.conda
Requires-Dist: birdhousebuilder.recipe.supervisor
Requires-Dist: setuptools
Requires-Dist: zc.buildout
Requires-Dist: zc.recipe.egg
Provides-Extra: tests
Requires-Dist: manuel; extra == 'tests'
Requires-Dist: zc.buildout; extra == 'tests'
Requires-Dist: zope.testing; extra == 'tests'
